sl3aio/__init__.py
sl3aio/dataparser.py
sl3aio/easytable.py
sl3aio/executor.py
sl3aio/table.py
test/__init__.py
test/test.py
sl3aio-1.3.0rc1.dist-info/LICENSE
sl3aio-1.3.0rc1.dist-info/METADATA
sl3aio-1.3.0rc1.dist-info/WHEEL
sl3aio-1.3.0rc1.dist-info/top_level.txt
sl3aio-1.3.0rc1.dist-info/RECORD
