Metadata-Version: 2.2
Name: sl3aio
Version: 1.3.0rc1
Summary: A simple and efficient Python library for asynchronous use of SQLite3 with a set of useful tools and interfaces.
Author-email: Nedelis <dimoshunya@gmail.com>
Maintainer-email: Nedelis <dimoshunya@gmail.com>
License: BSD 3-Clause License
Project-URL: Homepage, https://github.com/Nedelis/sl3aio
Project-URL: Documentation, https://sl3aio.readthedocs.io
Project-URL: Source, https://github.com/Nedelis/sl3aio/master/src/sl3aio
Project-URL: Repository, https://github.com/Nedelis/sl3aio
Project-URL: Bug Reports, https://github.com/Nedelis/sl3aio/issues
Keywords: database,development,sqlite,sl3,async
Classifier: Development Status :: 4 - Beta
Classifier: Intended Audience :: Developers
Classifier: Topic :: Database
Classifier: License :: OSI Approved :: BSD License
Classifier: Programming Language :: Python :: 3.12
Classifier: Programming Language :: Python :: 3.13
Requires-Python: >=3.12
License-File: LICENSE
